{
  "pendentes": [
    {
      "descricao": "Tarefa exemplo 12345",
      "data_limite": "28/11/2020",
      "responsavel": "João",
      "id": "m83XRJ3N2lnCejW5NTWis"
    },
    {
      "descricao": "Tarefa exemplo 54321",
      "data_limite": "29/11/2020",
      "responsavel": "Pedro",
      "id": "H88C6-Nb5spZKV3AQp4sE"
    },
    {
      "descricao": "Tarefa exemplo 21",
      "data_limite": "18/12/2020",
      "responsavel": "João",
      "id": "iVsowoyQgMyBEKNLJtFgW"
    },
    {
      "descricao": "Tarefa 123",
      "data_limite": "20/11/2020",
      "responsavel": "Pedro",
      "id": "v5-QecZswcE5h5YmJ_fSP"
    }
  ],
  "terminadas": [
    {
      "id": "4",
      "descricao": "Tarefa exemplo 4",
      "responsavel": "Exemplo 2",
      "data_limite": "17/11/2020",
      "resolvida": "Sim"
    },
    {
      "id": "5",
      "descricao": "Tarefa exemplo 5",
      "responsavel": "Exemplo 3",
      "data_limite": "17/11/2020",
      "resolvida": "Sim"
    },
    {
      "id": "6",
      "descricao": "Tarefa exemplo 6",
      "responsavel": "Exemplo 3",
      "data_limite": "17/11/2020",
      "resolvida": "Cancelada"
    },
    {
      "id": "2",
      "descricao": "Tarefa exemplo 2",
      "responsavel": "Exemplo 2",
      "data_limite": "17/11/2020",
      "resolvida": "Sim"
    },
    {
      "id": "3",
      "descricao": "Tarefa exemplo 3",
      "responsavel": "Exemplo 2",
      "data_limite": "17/11/2020",
      "resolvida": "Cancelada"
    },
    {
      "descricao": "Tarefa 102839012903",
      "data_limite": "24/11/2020",
      "responsavel": "João",
      "id": "eqDmjT2Lu86Ggcbb6glf_",
      "resolvida": "Cancelada"
    }
  ]
}